yandex_gpt/__init__.py
yandex_gpt/config_manager.py
yandex_gpt/thread.py
yandex_gpt/yandex_gpt.py
yandexgpt_python-0.2.3.dist-info/LICENSE
yandexgpt_python-0.2.3.dist-info/METADATA
yandexgpt_python-0.2.3.dist-info/WHEEL
yandexgpt_python-0.2.3.dist-info/top_level.txt
yandexgpt_python-0.2.3.dist-info/RECORD
