Metadata-Version: 2.1
Name: yandexgpt-python
Version: 0.2.3
Summary: A Python SDK for interacting with the YandexGPT API.
Home-page: https://github.com/allseeteam/yandexgpt-python
Author: ALL SEE LLC
Author-email: info@allsee.team
Classifier: Programming Language :: Python :: 3
Classifier: License :: OSI Approved :: MIT License
Classifier: Operating System :: OS Independent
Requires-Python: >=3.6
License-File: LICENSE
Requires-Dist: aiohttp ==3.9.3
Requires-Dist: cryptography ==42.0.5
Requires-Dist: PyJWT ==2.8.0
Requires-Dist: requests ==2.31.0
